mrjpacking/__init__.py
mrjpacking/cache_cleaner.py
mrjpacking/camera_module.py
mrjpacking/constants.py
mrjpacking/display_tracking_id_on_frame.py
mrjpacking/file_management.py
mrjpacking/main.py
mrjpacking/menu.py
mrjpacking/motion_detector.py
mrjpacking/order_counter.py
mrjpacking/overlay_module.py
mrjpacking/qr_scanner.py
mrjpacking/sound_module.py
mrjpacking/tracking_module.py
mrjpacking/sound/3beeps-108353.mp3
mrjpacking-0.4.28.dist-info/METADATA
mrjpacking-0.4.28.dist-info/WHEEL
mrjpacking-0.4.28.dist-info/entry_points.txt
mrjpacking-0.4.28.dist-info/top_level.txt
mrjpacking-0.4.28.dist-info/RECORD
