Metadata-Version: 2.1
Name: mrjpacking
Version: 0.4.28
Summary: Theo dõi đóng gói sản phẩm sàn thương mại điện tử
Author: Justin Nguyễn
Author-email: duchuy_1997@hotmail.com
Requires-Python: >=3.6
Requires-Dist: pyfiglet
Requires-Dist: colorama
Requires-Dist: keyboard
Requires-Dist: numpy
Requires-Dist: opencv-python
Requires-Dist: pygame
Requires-Dist: pyzbar
Requires-Dist: pygrabber
Requires-Dist: packaging
Requires-Dist: timedelta
